CHANGES.txt
LICENSE.txt
MANIFEST.in
README.md
setup.py
supervisor_cache/__init__.py
supervisor_cache/controllerplugin.py
supervisor_cache/rpcinterface.py
supervisor_cache.egg-info/PKG-INFO
supervisor_cache.egg-info/SOURCES.txt
supervisor_cache.egg-info/dependency_links.txt
supervisor_cache.egg-info/namespace_packages.txt
supervisor_cache.egg-info/not-zip-safe
supervisor_cache.egg-info/requires.txt
supervisor_cache.egg-info/top_level.txt
supervisor_cache/tests/__init__.py
supervisor_cache/tests/test_controllerplugin.py
supervisor_cache/tests/test_rpcinterface.py