Metadata-Version: 1.1
Name: supervisor-cache
Version: 1.0.0
Summary: supervisor_cache RPC extension for supervisor
Home-page: https://github.com/mnaberez/supervisor_cache
Author: Mike Naberezny
Author-email: mike@naberezny.com
License: License :: OSI Approved :: BSD License
Platform: UNKNOWN
Classifier: Development Status :: 5 - Production/Stable
Classifier: Environment :: No Input/Output (Daemon)
Classifier: Intended Audience :: System Administrators
Classifier: License :: OSI Approved :: BSD License
Classifier: Natural Language :: English
Classifier: Operating System :: POSIX
Classifier: Programming Language :: Python :: 2
Classifier: Programming Language :: Python :: 2.6
Classifier: Programming Language :: Python :: 2.7
Classifier: Programming Language :: Python :: 3
Classifier: Programming Language :: Python :: 3.2
Classifier: Programming Language :: Python :: 3.3
Classifier: Topic :: System :: Boot
Classifier: Topic :: System :: Systems Administration
